{"cameraMode":{"drawMode":0,"name":"Shaded","section":"Shading Mode"},"sceneLighting":true,"audioPlay":false,"sceneViewState":{"m_AlwaysRefresh":false,"showFog":true,"showSkybox":true,"showFlares":true,"showImageEffects":true,"showParticleSystems":true,"showVisualEffectGraphs":true,"m_FxEnabled":true},"in2DMode":false,"pivot":{"x":0.9440679550170898,"y":0.0659501850605011,"z":-0.09827196598052979},"rotation":{"x":-0.3292449116706848,"y":0.20533841848373414,"z":-0.07359341531991959,"w":-0.9187352061271668},"size":20.22369956970215,"orthographic":false}